MANIFEST.in
setup.cfg
setup.py
TracMacOSTheme.egg-info/PKG-INFO
TracMacOSTheme.egg-info/SOURCES.txt
TracMacOSTheme.egg-info/dependency_links.txt
TracMacOSTheme.egg-info/entry_points.txt
TracMacOSTheme.egg-info/requires.txt
TracMacOSTheme.egg-info/top_level.txt
tracmacos/__init__.py
tracmacos/theme.py
tracmacos/htdocs/about_trac_16_x_16.png
tracmacos/htdocs/active.png
tracmacos/htdocs/animatedcollapse.js
tracmacos/htdocs/bg1.png
tracmacos/htdocs/btn.png
tracmacos/htdocs/btnbg_32.png
tracmacos/htdocs/btnbg_64.png
tracmacos/htdocs/btnhover.png
tracmacos/htdocs/dev_trac_16_x_16.png
tracmacos/htdocs/dk_admin.png
tracmacos/htdocs/dk_bug.png
tracmacos/htdocs/dk_builds.png
tracmacos/htdocs/dk_default.png
tracmacos/htdocs/dk_downl.png
tracmacos/htdocs/dk_finder.png
tracmacos/htdocs/dk_finderb.jpg
tracmacos/htdocs/dk_milestone.png
tracmacos/htdocs/dk_notepad.jpg
tracmacos/htdocs/dk_prefs.png
tracmacos/htdocs/dk_pydoc.png
tracmacos/htdocs/dk_search.png
tracmacos/htdocs/dk_search2.png
tracmacos/htdocs/dk_tickets.png
tracmacos/htdocs/dk_timeline.png
tracmacos/htdocs/dk_tofu.png
tracmacos/htdocs/dk_transmission.png
tracmacos/htdocs/dk_wiki.png
tracmacos/htdocs/downl_trac_16_x_16.png
tracmacos/htdocs/download_trac_16_x_16.png
tracmacos/htdocs/extlink.png
tracmacos/htdocs/fl.png
tracmacos/htdocs/fl_alt.png
tracmacos/htdocs/hbar.png
tracmacos/htdocs/help_trac_16_x_16.png
tracmacos/htdocs/jquery.cookie.js
tracmacos/htdocs/jquery.jqDock.min.js
tracmacos/htdocs/log_trac_16_x_16.png
tracmacos/htdocs/logging_trac_16_x_16.png
tracmacos/htdocs/login_trac_16_x_16.png
tracmacos/htdocs/logout_trac_16_x_16.png
tracmacos/htdocs/mac.css
tracmacos/htdocs/more_trac_16_x_16.png
tracmacos/htdocs/netsurf.css
tracmacos/htdocs/prefs_trac_16_x_16.png
tracmacos/htdocs/rpc.png
tracmacos/htdocs/sbbottom.PNG
tracmacos/htdocs/sbbox.PNG
tracmacos/htdocs/sbtop.PNG
tracmacos/htdocs/screenshot.png
tracmacos/htdocs/screenshot_tbmin.png
tracmacos/htdocs/search_trac_16_x_16.png
tracmacos/htdocs/searchbox.png
tracmacos/htdocs/tb_admin.png
tracmacos/htdocs/tb_bug.gif
tracmacos/htdocs/tb_builds.png
tracmacos/htdocs/tb_finder.png
tracmacos/htdocs/tb_finder2.png
tracmacos/htdocs/tb_list.png
tracmacos/htdocs/tb_mac.png
