Metadata-Version: 1.0
Name: TracMacOSTheme
Version: 1.0.3
Summary: Trac theme to make it look like Mac OS
Home-page: http://trac-hacks.org/wiki/TracMacTheme
Author: Olemis Lang
Author-email: olemis+trac@gmail.com
License: GNU GPL v2
Keywords: trac plugin theme
Platform: UNKNOWN
Classifier: Development Status :: 4 - Beta
Classifier: Environment :: MacOS X
Classifier: Environment :: MacOS X :: Aqua
Classifier: Environment :: Plugins
Classifier: Environment :: Web Environment
Classifier: Framework :: Trac
Classifier: Intended Audience :: Developers
Classifier: Intended Audience :: Information Technology
Classifier: Intended Audience :: System Administrators
Classifier: License :: OSI Approved :: GNU General Public License (GPL)
Classifier: Natural Language :: English
Classifier: Natural Language :: Spanish
Classifier: Operating System :: OS Independent
Classifier: Programming Language :: Python
Classifier: Programming Language :: Python :: 2.4
Classifier: Programming Language :: Python :: 2.5
Classifier: Programming Language :: Python :: 2.6
Classifier: Topic :: Internet :: WWW/HTTP
Classifier: Topic :: Software Development :: Bug Tracking
Classifier: Topic :: Software Development :: User Interfaces
